telebot/__init__.py
telebot/api.py
telebot/callback_data.py
telebot/check_text.py
telebot/filters.py
telebot/flood_control.py
telebot/formatting.py
telebot/graceful_shutdown.py
telebot/helpers.py
telebot/metrics.py
telebot/py.typed
telebot/runner.py
telebot/storages/__init__.py
telebot/storages/base_storage.py
telebot/storages/memory_storage.py
telebot/storages/pickle_storage.py
telebot/storages/redis_storage.py
telebot/test_util.py
telebot/types/__init__.py
telebot/types/constants.py
telebot/types/service.py
telebot/util.py
telebot/webhook.py
telebot_against_war-0.7.14.dist-info/LICENSE
telebot_against_war-0.7.14.dist-info/METADATA
telebot_against_war-0.7.14.dist-info/WHEEL
telebot_against_war-0.7.14.dist-info/RECORD
