Metadata-Version: 2.1
Name: telebot-against-war
Version: 0.7.14
Summary: Async-first fork of pyTelegramBotApi
Home-page: https://github.com/bots-against-war/telebot
License: GPL-2.0-only
Author: Igor Vaiman
Author-email: gosha.vaiman@gmail.com
Requires-Python: >=3.9,<4.0
Classifier: License :: OSI Approved :: GNU General Public License v2 (GPLv2)
Classifier: Programming Language :: Python :: 3
Classifier: Programming Language :: Python :: 3.9
Classifier: Programming Language :: Python :: 3.10
Classifier: Programming Language :: Python :: 3.11
Classifier: Programming Language :: Python :: 3.12
Requires-Dist: aiohttp (>=3.9.5,<4.0.0)
Requires-Dist: typing-extensions (>=4.2.0,<5.0.0)
Requires-Dist: ujson (>=5.3.0,<6.0.0)
Project-URL: Repository, https://github.com/bots-against-war/telebot
